sensecam_control/__init__.py
sensecam_control/onvif_config.py
sensecam_control/onvif_control.py
sensecam_control/vapix_config.py
sensecam_control/vapix_control.py
so_ptz_control-1.1.0.dist-info/LICENSE.txt
so_ptz_control-1.1.0.dist-info/METADATA
so_ptz_control-1.1.0.dist-info/WHEEL
so_ptz_control-1.1.0.dist-info/top_level.txt
so_ptz_control-1.1.0.dist-info/RECORD
