Metadata-Version: 2.1
Name: so-ptz-control
Version: 1.1.0
Summary: Implementation of python functions for control and configuration of Axis cameras using Vapix/Onvif.
Home-page: https://github.com/WendShadow/ptz-control.git
Author: so
Author-email: Wendshadow118@gmail.com
License: MIT
Keywords: ONVIF,vapix,camera
Platform: UNKNOWN
Classifier: Programming Language :: Python :: 3
Classifier: License :: OSI Approved :: MIT License
Classifier: Operating System :: OS Independent
Requires-Python: >=3.6
Requires-Dist: beautifulsoup4 (==4.12.2)
Requires-Dist: onvif-zeep (==0.2.12)
Requires-Dist: requests (==2.28.1)
Requires-Dist: urllib3 (==1.25.7)
